tox_poetry_installer/__about__.py
tox_poetry_installer/__init__.py
tox_poetry_installer/_poetry.py
tox_poetry_installer/constants.py
tox_poetry_installer/exceptions.py
tox_poetry_installer/hooks.py
tox_poetry_installer/installer.py
tox_poetry_installer/logger.py
tox_poetry_installer/py.typed
tox_poetry_installer/utilities.py
tox_poetry_installer-0.10.3.dist-info/LICENSE.md
tox_poetry_installer-0.10.3.dist-info/METADATA
tox_poetry_installer-0.10.3.dist-info/WHEEL
tox_poetry_installer-0.10.3.dist-info/entry_points.txt
tox_poetry_installer-0.10.3.dist-info/RECORD
