Metadata-Version: 2.1
Name: tox-poetry-installer
Version: 0.10.3
Summary: A plugin for Tox that lets you install test environment dependencies from the Poetry lockfile
Home-page: https://github.com/enpaul/tox-poetry-installer/
License: MIT
Keywords: tox,poetry,plugin
Author: Ethan Paul
Author-email: 24588726+enpaul@users.noreply.github.com
Requires-Python: >=3.7,<4.0
Classifier: Development Status :: 4 - Beta
Classifier: Environment :: Plugins
Classifier: Framework :: tox
Classifier: Intended Audience :: Developers
Classifier: License :: OSI Approved :: MIT License
Classifier: Natural Language :: English
Classifier: Operating System :: OS Independent
Classifier: Programming Language :: Python :: 3
Classifier: Programming Language :: Python :: 3.7
Classifier: Programming Language :: Python :: 3.8
Classifier: Programming Language :: Python :: 3.9
Classifier: Programming Language :: Python :: 3.10
Classifier: Programming Language :: Python :: 3.11
Classifier: Programming Language :: Python :: 3
Classifier: Programming Language :: Python :: 3.10
Classifier: Programming Language :: Python :: 3.11
Classifier: Programming Language :: Python :: 3.7
Classifier: Programming Language :: Python :: 3.8
Classifier: Programming Language :: Python :: 3.9
Classifier: Programming Language :: Python :: Implementation :: CPython
Provides-Extra: poetry
Requires-Dist: cleo (>=1.0,<3.0) ; extra == "poetry"
Requires-Dist: poetry (>=1.2.0,<1.5.0) ; extra == "poetry"
Requires-Dist: poetry-core (>=1.1.0,<2.0.0)
Requires-Dist: tox (>=3.8.0,<4.0.0)
Project-URL: Repository, https://github.com/enpaul/tox-poetry-installer/
